bullet/__init__.py
bullet/charDef.py
bullet/client.py
bullet/colors.py
bullet/cursor.py
bullet/emojis.py
bullet/keyhandler.py
bullet/styles.py
bullet/utils.py
tests/client_bullet_test.py
tests/client_check_test.py
tests/client_input_test.py
tests/client_numbers_test.py
tests/client_password_test.py
tests/client_scrollbar_test.py
tests/client_slideprompt_test.py
tests/client_verticalprompt_test.py
tests/client_yesno_test.py
tests/cursor_test.py
tests/keyhandler_test.py
tests/utils_test.py
BulletPrompt-2.2.3.dist-info/LICENSE
BulletPrompt-2.2.3.dist-info/METADATA
BulletPrompt-2.2.3.dist-info/WHEEL
BulletPrompt-2.2.3.dist-info/top_level.txt
BulletPrompt-2.2.3.dist-info/RECORD
