Metadata-Version: 2.2
Name: BulletPrompt
Version: 2.2.3
Summary: Interactive prompts made simple. Maintained version of Bullet.
Home-page: https://github.com/danner26/BulletPrompt
Author: danner26
Author-email: Daniel Anner <daniel.anner@danstechsupport.com>, Greg Walsh <greg.walsh@danstechsupport.com>
Maintainer-email: Dan's Tech Support LLC <hello@danstechsupport.com>
License: MIT
Project-URL: Homepage, https://pypi.org/project/BulletPrompt/
Project-URL: Source, https://github.com/danner26/BulletPrompt
Project-URL: Documentation, https://github.com/danner26/BulletPrompt/blob/master/DOCUMENTATION.md
Project-URL: Bug Reports, https://github.com/danner26/BulletPrompt/issues
Project-URL: Changelog, https://github.com/danner26/BulletPrompt/releases
Keywords: prompts,pypi-package,python3,bullet,BulletPrompt
Requires-Python: >=3.6
License-File: LICENSE
Provides-Extra: dev
Requires-Dist: ruff; extra == "dev"
Requires-Dist: pytest; extra == "dev"
Requires-Dist: pre-commit; extra == "dev"
Requires-Dist: pytest-mock; extra == "dev"
Requires-Dist: uv; extra == "dev"
Dynamic: author
Dynamic: home-page
Dynamic: requires-python
